mitba/__init__.py
mitba/python_compat.py
mitba-1.1.1.dist-info/AUTHORS
mitba-1.1.1.dist-info/LICENSE
mitba-1.1.1.dist-info/METADATA
mitba-1.1.1.dist-info/WHEEL
mitba-1.1.1.dist-info/pbr.json
mitba-1.1.1.dist-info/top_level.txt
mitba-1.1.1.dist-info/RECORD
