Metadata-Version: 2.1
Name: mitba
Version: 1.1.1
Summary: Python library for caching results from functions and methods
Home-page: https://github.com/Infinidat/mitba
Author: Infinidat Ltd.
Author-email: info@infinidat.com
License: BSD3
Platform: UNKNOWN
Classifier: Programming Language :: Python :: 2.7
Classifier: Programming Language :: Python :: 3.4
Classifier: Programming Language :: Python :: 3.5
Classifier: Programming Language :: Python :: 3.6
Classifier: Programming Language :: Python :: 3.7
Requires-Dist: flux
Requires-Dist: Logbook (>=0.12.2)
Provides-Extra: doc
Requires-Dist: alabaster ; extra == 'doc'
Requires-Dist: docutils ; extra == 'doc'
Requires-Dist: releases ; extra == 'doc'
Requires-Dist: Sphinx (>=1.7.1) ; extra == 'doc'
Provides-Extra: testing
Requires-Dist: pylint ; extra == 'testing'
Requires-Dist: pytest-cov ; extra == 'testing'
Requires-Dist: pytest ; (python_version < "3.0") and extra == 'testing'
Requires-Dist: pytest (>4.0) ; (python_version >= "3.0") and extra == 'testing'
